efpodsanalyzer/EFPAConfig.json
efpodsanalyzer/__init__.py
efpodsanalyzer/efpodsanalyzer.py
efpodsanalyzer/EFPADiagram/graph_circular.html
efpodsanalyzer/EFPADiagram/graph_force.html
efpodsanalyzer/EFPADiagram/index.html
efpodsanalyzer/EFPADiagram/css/style.css
efpodsanalyzer/EFPADiagram/js/dataTool.js
efpodsanalyzer/EFPADiagram/js/echarts.min.js
efpodsanalyzer/EFPADiagram/js/jquery.min.js
efpodsanalyzer/EFPADiagram/js/xml2json.min.js
efpodsanalyzer/template/data.json
efpodsanalyzer-0.2.6.dist-info/LICENSE
efpodsanalyzer-0.2.6.dist-info/METADATA
efpodsanalyzer-0.2.6.dist-info/WHEEL
efpodsanalyzer-0.2.6.dist-info/entry_points.txt
efpodsanalyzer-0.2.6.dist-info/top_level.txt
efpodsanalyzer-0.2.6.dist-info/RECORD
